README.rst
setup.py
mob_metric/__init__.py
mob_metric/metric.py
mob_metric.egg-info/PKG-INFO
mob_metric.egg-info/SOURCES.txt
mob_metric.egg-info/dependency_links.txt
mob_metric.egg-info/top_level.txt
mob_metric.egg-info/zip-safe