Metadata-Version: 1.1
Name: mob-metric
Version: 0.0.3
Summary: this is a tool package for mob_metric.
Home-page: https://github.com/pypa/sampleproject
Author: John
Author-email: erqinag@mobtech.com
License: MIT
Keywords: mob utils
Platform: UNKNOWN
Classifier: License :: OSI Approved :: MIT License
Classifier: Programming Language :: Python
Classifier: Intended Audience :: Developers
Classifier: Operating System :: OS Independent
